{"generated":1782621601,"totals":{"queries":63258,"blocked":6403,"block_rate":0.1012},"blocked_days":[{"date":"2026-06-28","total":183,"clients":{"192.168.1.32":{"b3706b4d147b338e455c61c61223fa3f03dc73242e377721029d95badedd4bc.us-east-1.prod.service.minerva.devices.a2z.com":59,"browser-intake-us5-datadoghq.com":24,"api.mixpanel.com":21,"sentry.io":18,"o1158394.ingest.us.sentry.io":5,"fbs.smoot.apple.com":4,"smoot-feedback.v.aaplimg.com":4,"appsgrowthpromo-pa.googleapis.com":3,"unagi-eu.amazon.com":3,"metrics.icloud.com":2,"in.appcenter.ms":2,"ic3.events.data.microsoft.com":2,"o4506664995192832.ingest.sentry.io":1,"emrmrs.cdn-settings.appsflyersdk.com":1,"emrmrs.launches.appsflyersdk.com":1,"metrics-config.icloud.com":1,"app-analytics-services.com":1,"crashlyticsreports-pa.googleapis.com":1,"googleads.g.doubleclick.net":1,"kvinit-prod.api.kochava.com":1,"api.bitdrift.io":1,"api.segment.io":1,"ogads-pa.googleapis.com":1,"growth-pa.googleapis.com":1},"10.10.10.10":{"http-intake.logs.us5.datadoghq.com":12},"192.168.1.34":{"b3706b4d147b338e455c61c61223fa3f03dc73242e377721029d95badedd4bc.us-east-1.prod.service.minerva.devices.a2z.com":9,"in.appcenter.ms":2,"metrics.icloud.com":1}}},{"date":"2026-06-27","total":1526,"clients":{"192.168.1.25":{"b3706b4d147b338e455c61c61223fa3f03dc73242e377721029d95badedd4bc.us-east-1.prod.service.minerva.devices.a2z.com":89,"98cd9fda0f5c966c153fce4484f8be3690c42508d9c8a35e544813238116c0b.us-east-1.prod.service.minerva.devices.a2z.com":38,"app-analytics-services.com":25,"app-measurement.com":25,"browser-intake-us5-datadoghq.com":22,"googleads.g.doubleclick.net":9,"unagi-eu.amazon.com":9,"firebaselogging-pa.googleapis.com":9,"api.mixpanel.com":7,"metrics.icloud.com":6,"sentry.io":6,"ic3.events.data.microsoft.com":6,"remote-data.asnapieu.com":6,"fbs.smoot.apple.com":5,"smoot-feedback.v.aaplimg.com":5,"teams.events.data.microsoft.com":5,"device-api.asnapieu.com":5,"www.googletagmanager.com":5,"pubads.g.doubleclick.net":5,"tpr0m7.launches.appsflyersdk.com":5,"ipv6-onprem.cws.conviva.com":4,"ipv4-onprem.cws.conviva.com":4,"crashlyticsreports-pa.googleapis.com":4,"o1064774.ingest.sentry.io":4,"firebase-settings.crashlytics.com":4,"odf.app-ads-services.com":4,"w3-reporting.reddit.com":4,"searchlabspartnerservice-pa.googleapis.com":3,"launches.appsflyer.com":3,"o1158394.ingest.us.sentry.io":3,"www.app-ads-services.com":3,"muf.app-ads-services.com":3,"tpr0m7.cdn-settings.appsflyersdk.com":3,"pixel-config.reddit.com":3,"bf10006sbr.bf.dynatrace.com":3,"api.bitdrift.io":2,"cws-iad4-slb10.conviva.com":2,"growth-pa.googleapis.com":2,"b68f56edeceb6d2e33ce6c5eafcdd3d62fdb0e25.ipv4.cws.conviva.com":2,"b68f56edeceb6d2e33ce6c5eafcdd3d62fdb0e25.ipv6.cws.conviva.com":2,"weather-analytics-events.apple.com":2,"prod-event-relay-weather-api.v.aaplimg.com":2,"mboxedge35.tt.omtrdc.net":2,"clienttracing-pa.googleapis.com":1,"metrics-config.icloud.com":1,"api.instabug.com":1,"api.permutive.app":1,"kvinit-prod.api.kochava.com":1,"b68f56edeceb6d2e33ce6c5eafcdd3d62fdb0e25.cws.conviva.com":1,"usage-ping.brave.com":1,"ogads-pa.googleapis.com":1,"securepubads.g.doubleclick.net":1,"stats.wp.com":1,"cm.g.doubleclick.net":1,"collect.tealiumiq.com":1,"int.dewrain.life":1,"ipv4.cws.conviva.com":1,"nexus.ensighten.com":1,"siteintercept.qualtrics.com":1,"prodlb.siteintercept.qualtrics.com.cdn.cloudflare.net":1,"m5o81ypttbseaam5b7uxd6tfv5557wbzrrear6fra9dfae8ddf77133eam1.e.aa.online-metrix.net":1,"eu-aa.online-metrix.net":1,"dpm.demdex.net":1,"gslb-2.demdex.net":1,"cdn.taboola.com":1,"a-9c6kp.config.emb-api.com":1,"a-9c6kp.data.emb-api.com":1,"analytics.query.yahoo.com":1,"pbs.yahoo.com":1,"edge-prebid-pbs.g03.yahoodns.net":1,"geo.yahoo.com":1,"ups.analytics.yahoo.com":1,"dcs-ups.g03.yahoodns.net":1,"pagead2.googlesyndication.com":1,"census-app-x.scorecardresearch.com":1,"region1.app-analytics-services.com":1,"experiments.apple.com":1},"10.10.10.10":{"http-intake.logs.us5.datadoghq.com":195},"192.168.1.32":{"browser-intake-us5-datadoghq.com":202,"b3706b4d147b338e455c61c61223fa3f03dc73242e377721029d95badedd4bc.us-east-1.prod.service.minerva.devices.a2z.com":149,"unagi-eu.amazon.com":133,"app-analytics-services.com":53,"o1158394.ingest.us.sentry.io":48,"app-measurement.com":37,"firebaselogging-pa.googleapis.com":18,"logs-16c9d93d.eu.v2.we-stats.com":18,"ic3.events.data.microsoft.com":12,"googleads.g.doubleclick.net":10,"tpr0m7.launches.appsflyersdk.com":10,"metrics.icloud.com":9,"tpr0m7.cdn-settings.appsflyersdk.com":9,"api.mixpanel.com":8,"w3-reporting.reddit.com":7,"api.bitdrift.io":7,"prodlb.siteintercept.qualtrics.com.cdn.cloudflare.net":7,"sentry.io":6,"cdn.p-n.io":5,"ogads-pa.googleapis.com":5,"eu-aa.online-metrix.net":5,"odf.app-ads-services.com":5,"collect.tealiumiq.com":5,"o4504611328622592.ingest.sentry.io":5,"fbs.smoot.apple.com":5,"smoot-feedback.v.aaplimg.com":5,"growth-pa.googleapis.com":4,"api.instabug.com":4,"api.permutive.app":4,"b68f56edeceb6d2e33ce6c5eafcdd3d62fdb0e25.cws.conviva.com":4,"muf.app-ads-services.com":4,"ad.doubleclick.net":4,"www.googletagmanager.com":4,"region1.app-analytics-services.com":4,"prod-event-relay-notes-api.v.aaplimg.com":4,"device-api.asnapieu.com":4,"analytics.console-mobile.aws.dev":4,"post-auth.iad.prod.telemetry.console-mobile.aws.dev":4,"api-eu.mixpanel.com":3,"firebase-settings.crashlytics.com":3,"www.app-ads-services.com":3,"bf10006sbr.bf.dynatrace.com":3,"dpm.demdex.net":3,"int.vaicore.site":2,"o64374.ingest.sentry.io":2,"appsgrowthpromo-pa.googleapis.com":2,"in.appcenter.ms":2,"pixel-config.reddit.com":2,"crashlyticsreports-pa.googleapis.com":2,"remote-data.asnapieu.com":2,"ipv6-onprem.cws.conviva.com":2,"ipv4-onprem.cws.conviva.com":2,"int.akisinn.info":2,"gslb-2.demdex.net":2,"zn2rtgq6h2yqvzry1-lloydsbankinggroup.siteintercept.qualtrics.com":2,"int.dewrain.site":2,"sdk.us-10.braze.com":2,"int.akisinn.site":2,"int.vaicore.xyz":2,"int.vaicore.store":2,"int.dewrain.world":2,"cws-iad4-slb9.conviva.com":2,"news.iadsdk.apple.com":1,"c6thn4.launches.appsflyersdk.com":1,"cf.iadsdk.apple.com":1,"partiality.itunes.apple.com":1,"cf.iadsdk.apple.com.akadns.net":1,"cws-euw1.conviva.com":1,"sdk.fra-01.braze.eu":1,"sdk.fra-01.braze.eu.cdn.cloudflare.net":1,"sentry-2.boxine.de":1,"sentry-1.eu-central-1.prod.tonie.cloud":1,"uct.service.usercentrics.eu":1,"mobile.eum-appdynamics.com":1,"col.eum-appdynamics.com":1,"collect-eu-central-1.tealiumiq.com":1,"visitor-service-eu-central-1.tealiumiq.com":1,"djr064j7e73xjprggqtctf2mxtpxukecqzuew3vvc9b9cd292a747362am1.e.aa.online-metrix.net":1,"log-beed83c9.eu.v2.we-stats.com":1,"djr064j7e73xjprggqtctf2mxtpxukecqzuew3vvcf7b18eeef915c3dam1.e.aa.online-metrix.net":1,"fast.nexx360.io":1,"ms.applovin.com":1,"c6thn4.cdn-settings.appsflyersdk.com":1,"static.hotjar.com":1,"static-cdn.hotjar.com":1,"region1.analytics.google.com":1,"api3.branch.io":1,"resolver.confidence.dev":1,"sdk.fra-02.braze.eu":1,"js-eu1.hs-scripts.com":1,"dit.whatsapp.net":1,"notes-analytics-events.apple.com":1,"b68f56edeceb6d2e33ce6c5eafcdd3d62fdb0e25.ipv4.cws.conviva.com":1,"b68f56edeceb6d2e33ce6c5eafcdd3d62fdb0e25.ipv6.cws.conviva.com":1,"o1064774.ingest.sentry.io":1,"launches.appsflyer.com":1,"iwmapapi.americanexpress.com":1,"zndhztugwqhlulqht-aexpfeedback.siteintercept.qualtrics.com":1,"cws-iad4-slb10.conviva.com":1,"m5o81yptmpyh3o7ml4rykp5mowxoqvnkc3ikrneh38ca09aaf12ffb92am1.e.aa.online-metrix.net":1,"liveapi-cached.yext.com":1,"aa.online-metrix.net":1,"cws-us-west-1.conviva.com":1,"m5o81yptmpyh3o7ml4rykp5mowxoqvnkc3ikrneh555292f44cefcea1am1.e.aa.online-metrix.net":1,"optimisation.data.lloydsbankinggroup.com":1,"m5o81yptmpyh3o7ml4rykp5mowxoqvnkc3ikrneh45d92c50c2f4287fam1.e.aa.online-metrix.net":1,"m5o81yptmpyh3o7ml4rykp5mowxoqvnkc3ikrneh886882df2a774b3aam1.e.aa.online-metrix.net":1,"kvinit-prod.api.kochava.com":1,"int.dewrain.life":1,"pre-auth.iad.prod.telemetry.console-mobile.aws.dev":1,"o4506664995192832.ingest.sentry.io":1,"emrmrs.cdn-settings.appsflyersdk.com":1,"emrmrs.launches.appsflyersdk.com":1,"metrics-config.icloud.com":1,"iadsdk.apple.com":1}}},{"date":"2026-06-26","total":1455,"clients":{"192.168.1.25":{"browser-intake-us5-datadoghq.com":182,"98cd9fda0f5c966c153fce4484f8be3690c42508d9c8a35e544813238116c0b.us-east-1.prod.service.minerva.devices.a2z.com":167,"b3706b4d147b338e455c61c61223fa3f03dc73242e377721029d95badedd4bc.us-east-1.prod.service.minerva.devices.a2z.com":139,"unagi-eu.amazon.com":70,"app-analytics-services.com":52,"sentry.io":51,"app-measurement.com":49,"firebaselogging-pa.googleapis.com":27,"o1158394.ingest.us.sentry.io":22,"api.bitdrift.io":21,"api.mixpanel.com":17,"tpr0m7.launches.appsflyersdk.com":14,"tpr0m7.cdn-settings.appsflyersdk.com":12,"odf.app-ads-services.com":11,"w3-reporting.reddit.com":11,"o64374.ingest.sentry.io":11,"smoot-feedback.v.aaplimg.com":10,"metrics.icloud.com":10,"fbs.smoot.apple.com":9,"googleads.g.doubleclick.net":9,"c6thn4.launches.appsflyersdk.com":8,"teams.events.data.microsoft.com":7,"www.app-ads-services.com":7,"muf.app-ads-services.com":7,"www.googletagmanager.com":7,"in.appcenter.ms":6,"ic3.events.data.microsoft.com":6,"crashlyticsreports-pa.googleapis.com":6,"growth-pa.googleapis.com":5,"pixel-config.reddit.com":5,"pubads.g.doubleclick.net":5,"www.google-analytics.com":5,"vmss-clarity-ingest-eus-d.eastus.cloudapp.azure.com":5,"ad.doubleclick.net":4,"o1064774.ingest.sentry.io":4,"cws-iad4-slb10.conviva.com":4,"region1.google-analytics.com":4,"region1.app-analytics-services.com":4,"cdn.p-n.io":4,"usage-ping.brave.com":3,"csp.withgoogle.com":3,"firebase-settings.crashlytics.com":3,"b68f56edeceb6d2e33ce6c5eafcdd3d62fdb0e25.ipv4.cws.conviva.com":3,"b68f56edeceb6d2e33ce6c5eafcdd3d62fdb0e25.ipv6.cws.conviva.com":3,"ipv6-onprem.cws.conviva.com":3,"ipv4-onprem.cws.conviva.com":3,"device-api.asnapieu.com":3,"ogads-pa.clients6.google.com":3,"js-agent.newrelic.com":3,"googletagmanager.com":3,"in-ftd-269.nl3.vip.prod.criteo.com":3,"api.instabug.com":3,"api.permutive.app":3,"b68f56edeceb6d2e33ce6c5eafcdd3d62fdb0e25.cws.conviva.com":3,"combine.asnapieu.com":3,"sdk.fra-01.braze.eu.cdn.cloudflare.net":3,"metrics-config.icloud.com":2,"ogads-pa.googleapis.com":2,"remote-data.asnapieu.com":2,"launches.appsflyer.com":2,"o33249.ingest.us.sentry.io":2,"gum.criteo.com":2,"www.clarity.ms":2,"vmss-clarity-tag-sln.switzerlandnorth.cloudapp.azure.com":2,"o4506664995192832.ingest.sentry.io":2,"emrmrs.cdn-settings.appsflyersdk.com":2,"emrmrs.launches.appsflyersdk.com":2,"pagead2.googlesyndication.com":2,"dit.whatsapp.net":2,"collect.tealiumiq.com":2,"region1.app-measurement.com":2,"sdk.fra-01.braze.eu":2,"weather-analytics-events.apple.com":2,"prod-event-relay-weather-api.v.aaplimg.com":2,"log-beed83c9.eu.v2.we-stats.com":2,"api-eu.mixpanel.com":2,"iadsdk.apple.com":2,"cdn-settings.appsflyersdk.com":1,"firebaselogging.googleapis.com":1,"ucm-eu.verint-cdn.com":1,"eum.instana.io":1,"c.go-mpulse.net":1,"eum-eu-west-1.instana.io":1,"se.monetate.net":1,"sc-static.net":1,"js.adsrvr.org":1,"bat.bing.com":1,"ads.celtra.com":1,"p.teads.tv":1,"10964987.collect.igodigital.com":1,"dpm.demdex.net":1,"gslb-2.demdex.net":1,"collect-eu-west-1.tealiumiq.com":1,"zn6mcrij6xncfajof-adidastrial.siteintercept.qualtrics.com":1,"tags.creativecdn.com":1,"www.dwin1.com":1,"match.adsrvr.org":1,"cm.g.doubleclick.net":1,"nova-collector-1192479543.us-east-1.elb.amazonaws.com":1,"visitor-service-eu-west-1.tealiumiq.com":1,"prodlb.siteintercept.qualtrics.com.cdn.cloudflare.net":1,"ct.pinterest.com":1,"px.ads.linkedin.com":1,"cdn.quantummetric.com":1,"ams.creativecdn.com":1,"adidas.d3.sc.omtrdc.net":1,"adobedc.demdex.net":1,"demdex.net.ssl.sc.omtrdc.net":1,"edge.adobedc.net":1,"adobedc.net.ssl.sc.omtrdc.net":1,"insights-collector.newrelic.com":1,"abt.nike.com":1,"fastly-tls12-insights-collector.newrelic.com":1,"nike.tt.omtrdc.net":1,"s.go-mpulse.net":1,"product-proxy-v2.adtech-prod.nikecloud.com":1,"ws.sessioncam.com":1,"f.monetate.net":1,"bam.nr-data.net":1,"ads.yahoo.com":1,"sync.outbrain.com":1,"pixel.rubiconproject.com":1,"nexus.ensighten.com":1,"f.monetate-prod.zone":1,"af.monetate.net":1,"sb.monetate.net":1,"d.monetate.net":1,"fastly-tls12-bam.nr-data.net":1,"analytics.tiktok.com":1,"pixel.rubiconproject.net.akadns.net":1,"chidc2.outbrain.org":1,"d.monetate-prod.zone":1,"zn2hn6hcwm3l4fwlo-jdgroupplc.siteintercept.qualtrics.com":1,"creativecdn.com":1,"www.googleadservices.com":1,"dynamic.criteo.com":1,"static.ads-twitter.com":1,"t.contentsquare.net":1,"static.criteo.net":1,"in-ftd-109.nl3.vip.prod.criteo.com":1,"in-ftd-172.nl3.vip.prod.criteo.com":1,"lantern.roeyecdn.com":1,"i.ctnsnet.com":1,"api.metrics.eu-south-2.iris.apx.amazon.dev":1,"kite.spicegems.org":1,"monorail-edge.shopifysvc.com":1,"a.pandect.es":1,"consents-v2.pandect.es":1,"invitejs.trustpilot.com":1,"cdn9.forter.com":1,"d81a0a0ea70f4684b73f0d64a90b6eb5-7ce243a1e1a2.cdn.forter.com":1,"cdn3.forter.com":1,"7ce243a1e1a2.cdn4.forter.com":1,"ls.hit.gemius.pl":1,"securepubads.g.doubleclick.net":1,"static.cloudflareinsights.com":1,"www.googletagservices.com":1,"sentry-2.boxine.de":1,"sentry-1.eu-central-1.prod.tonie.cloud":1,"uct.service.usercentrics.eu":1,"a.clarity.ms":1,"mobile.eum-appdynamics.com":1,"col.eum-appdynamics.com":1,"collect-eu-central-1.tealiumiq.com":1,"visitor-service-eu-central-1.tealiumiq.com":1,"djr064j7p4henhl7r6o7ijm6j62ipm2a423bv26r3105a1d2464c3be8am1.e.aa.online-metrix.net":1,"eu-aa.online-metrix.net":1,"djr064j7p4henhl7r6o7ijm6j62ipm2a423bv26r981dc1ac999aed39am1.e.aa.online-metrix.net":1,"int.vaicore.site":1,"sdk.us-10.braze.com":1,"int.akisinn.info":1,"int.dewrain.site":1,"int.akisinn.site":1,"int.vaicore.xyz":1,"int.vaicore.store":1,"int.dewrain.world":1},"10.10.10.10":{"http-intake.logs.us5.datadoghq.com":266}}},{"date":"2026-06-25","total":1019,"clients":{"192.168.1.12":{"browser-intake-us5-datadoghq.com":91,"b3706b4d147b338e455c61c61223fa3f03dc73242e377721029d95badedd4bc.us-east-1.prod.service.minerva.devices.a2z.com":66,"sentry.io":33,"app-analytics-services.com":26,"o1158394.ingest.us.sentry.io":19,"app-measurement.com":17,"device-api.asnapieu.com":8,"firebaselogging-pa.googleapis.com":8,"metrics.icloud.com":7,"api3.branch.io":7,"sdk.fra-01.braze.eu.cdn.cloudflare.net":7,"remote-data.asnapieu.com":6,"googleads.g.doubleclick.net":6,"sdk.fra-01.braze.eu":6,"fbs.smoot.apple.com":5,"smoot-feedback.v.aaplimg.com":5,"region1.app-measurement.com":5,"o1064774.ingest.sentry.io":4,"launches.appsflyer.com":4,"www.googletagmanager.com":4,"tpr0m7.cdn-settings.appsflyersdk.com":4,"api.permutive.app":4,"api.instabug.com":4,"b68f56edeceb6d2e33ce6c5eafcdd3d62fdb0e25.cws.conviva.com":4,"api.mixpanel.com":3,"ic3.events.data.microsoft.com":3,"teams.events.data.microsoft.com":3,"b68f56edeceb6d2e33ce6c5eafcdd3d62fdb0e25.ipv4.cws.conviva.com":3,"ipv4-onprem.cws.conviva.com":3,"ipv6-onprem.cws.conviva.com":3,"collect.tealiumiq.com":3,"tpr0m7.launches.appsflyersdk.com":3,"prod-event-relay-notes-api.v.aaplimg.com":3,"searchlabspartnerservice-pa.googleapis.com":2,"b68f56edeceb6d2e33ce6c5eafcdd3d62fdb0e25.ipv6.cws.conviva.com":2,"firebase-settings.crashlytics.com":2,"w3-reporting.reddit.com":2,"prod-event-relay-weather-api.v.aaplimg.com":2,"unagi-eu.amazon.com":2,"cws-iad1.conviva.com":2,"cf.iadsdk.apple.com.akadns.net":2,"api.lab.eu.amplitude.com":2,"amplitude.map.fastly.net":2,"dit.whatsapp.net":2,"in.appcenter.ms":1,"metrics-config.icloud.com":1,"clienttracing-pa.googleapis.com":1,"appsgrowthpromo-pa.googleapis.com":1,"ingest.appcenter.ms":1,"crashlyticsreports-pa.googleapis.com":1,"region1.app-analytics-services.com":1,"pixel-config.reddit.com":1,"weather-analytics-events.apple.com":1,"ogads-pa.googleapis.com":1,"growth-pa.googleapis.com":1,"ipv6.cws.conviva.com":1,"api.segment.io":1,"notes-analytics-events.apple.com":1,"usage-ping.brave.com":1,"int.dewrain.life":1,"cws-sjc2-rdc2.conviva.com":1,"cf.iadsdk.apple.com":1,"partiality.itunes.apple.com":1,"partiality.itunes-apple.com.akadns.net":1,"region1.google-analytics.com":1,"mobile-collector.eu01.nr-data.net":1,"mobile-collector.eu01.nr-data.net.cdn.cloudflare.net":1,"api-apm.instabug.com":1,"firebaselogging.googleapis.com":1,"resolver.confidence.dev":1,"sdk.fra-02.braze.eu":1,"www.app-ads-services.com":1,"odf.app-ads-services.com":1,"muf.app-ads-services.com":1,"sentry-2.boxine.de":1,"sentry-1.eu-central-1.prod.tonie.cloud":1,"uct.service.usercentrics.eu":1,"ogads-pa.clients6.google.com":1},"10.10.10.10":{"http-intake.logs.us5.datadoghq.com":188},"192.168.1.25":{"cdn.p-n.io":229,"b3706b4d147b338e455c61c61223fa3f03dc73242e377721029d95badedd4bc.us-east-1.prod.service.minerva.devices.a2z.com":68,"app-analytics-services.com":13,"api.mixpanel.com":10,"csp.withgoogle.com":8,"unagi-eu.amazon.com":6,"fbs.smoot.apple.com":6,"smoot-feedback.v.aaplimg.com":6,"ogads-pa.clients6.google.com":5,"browser-intake-us5-datadoghq.com":3,"metrics.icloud.com":3,"api3.branch.io":3,"o1158394.ingest.us.sentry.io":2,"app-measurement.com":2,"api.bitdrift.io":2,"firebaselogging-pa.googleapis.com":2,"mobiletelemetry.ebay.com":2,"sentry.io":2,"teams.events.data.microsoft.com":2,"api.segment.io":1,"w3-reporting.reddit.com":1,"cdn.branch.io":1,"tpr0m7.launches.appsflyersdk.com":1,"pixel-config.reddit.com":1,"int.vaicore.site":1,"sdk.us-10.braze.com":1,"int.akisinn.info":1,"firebase-settings.crashlytics.com":1,"api-eu.mixpanel.com":1,"ep2.facebook.com":1,"adf0901f1861.cdn4.forter.com":1,"bztld4-launches.appsflyersdk.com":1,"src.ebay-us.com":1,"h-ebay.online-metrix.net":1,"int.dewrain.site":1,"int.akisinn.site":1,"iadsdk.apple.com":1,"www.googletagmanager.com":1,"metrics-config.icloud.com":1,"o4506664995192832.ingest.sentry.io":1,"emrmrs.cdn-settings.appsflyersdk.com":1,"emrmrs.launches.appsflyersdk.com":1,"int.vaicore.xyz":1}}},{"date":"2026-06-24","total":1702,"clients":{"192.168.1.9":{"api.mixpanel.com":103,"sentry.io":81,"b3706b4d147b338e455c61c61223fa3f03dc73242e377721029d95badedd4bc.us-east-1.prod.service.minerva.devices.a2z.com":57,"browser-intake-us5-datadoghq.com":33,"app-measurement.com":14,"app-analytics-services.com":10,"o1158394.ingest.us.sentry.io":9,"region1.app-analytics-services.com":6,"ic3.events.data.microsoft.com":4,"api3.branch.io":4,"firebaselogging-pa.googleapis.com":4,"metrics.icloud.com":3,"teams.events.data.microsoft.com":3,"usage-ping.brave.com":3,"o1064774.ingest.sentry.io":3,"region1.google-analytics.com":3,"pagead2.googlesyndication.com":2,"securepubads.g.doubleclick.net":2,"tpr0m7.launches.appsflyersdk.com":2,"w3-reporting.reddit.com":2,"pixel-config.reddit.com":2,"unagi-eu.amazon.com":2,"growth-pa.googleapis.com":2,"cdn-settings.appsflyersdk.com":2,"device-api.asnapieu.com":2,"remote-data.asnapieu.com":2,"googleads.g.doubleclick.net":2,"launches.appsflyer.com":2,"metrics-config.icloud.com":1,"searchlabspartnerservice-pa.googleapis.com":1,"www.googletagservices.com":1,"static.adsafeprotected.com":1,"d162h6x3rxav67.cloudfront.net":1,"sdk.jeeng.com":1,"widgets.outbrain.com":1,"recirculation.spot.im":1,"cdn.valuad.cloud":1,"www.googletagmanager.com":1,"ssl.google-analytics.com":1,"hb-dot-valuad.appspot.com":1,"publisher-assets.spot.im":1,"direct-events-collector.spot.im":1,"ads-configs-cdn.openweb.com":1,"metrics-logger.spot.im":1,"pix.spot.im":1,"bi-events-collector.spot.im":1,"int.vaicore.site":1,"api.bitdrift.io":1,"tpr0m7.cdn-settings.appsflyersdk.com":1,"o64374.ingest.sentry.io":1,"c6thn4.cdn-settings.appsflyersdk.com":1,"weather-analytics-events.apple.com":1,"prod-event-relay-weather-api.v.aaplimg.com":1,"pubads.g.doubleclick.net":1,"collect.tealiumiq.com":1,"cdn-eu.dynamicyield.com":1,"st-eu.dynamicyield.com":1,"rcom-eu.dynamicyield.com":1,"gtm.wise.com":1,"o4506664995192832.ingest.sentry.io":1,"emrmrs.cdn-settings.appsflyersdk.com":1,"emrmrs.launches.appsflyersdk.com":1},"10.10.10.10":{"http-intake.logs.us5.datadoghq.com":224},"192.168.1.12":{"browser-intake-us5-datadoghq.com":185,"b3706b4d147b338e455c61c61223fa3f03dc73242e377721029d95badedd4bc.us-east-1.prod.service.minerva.devices.a2z.com":91,"unagi-eu.amazon.com":70,"app-measurement.com":37,"app-analytics-services.com":34,"o1158394.ingest.us.sentry.io":33,"api.bitdrift.io":22,"api3.branch.io":15,"region1.app-analytics-services.com":15,"device-api.asnapieu.com":13,"tpr0m7.launches.appsflyersdk.com":12,"remote-data.asnapieu.com":11,"w3-reporting.reddit.com":9,"firebaselogging-pa.googleapis.com":8,"ad.doubleclick.net":8,"googleads.g.doubleclick.net":8,"sentry.io":8,"api.instabug.com":7,"api.permutive.app":7,"ipv6-onprem.cws.conviva.com":6,"ping.chartbeat.net":6,"metrics.icloud.com":6,"fbs.smoot.apple.com":6,"smoot-feedback.v.aaplimg.com":6,"b68f56edeceb6d2e33ce6c5eafcdd3d62fdb0e25.cws.conviva.com":5,"region1.google-analytics.com":5,"www.googletagmanager.com":5,"cdn.branch.io":5,"a1-api-bbc-co-uk-cddc.at-o.net":5,"api.mixpanel.com":5,"cws-iad4-slb10.conviva.com":4,"ipv4-onprem.cws.conviva.com":4,"pubads.g.doubleclick.net":4,"api.segment.io":4,"o1064774.ingest.sentry.io":4,"launches.appsflyer.com":4,"cdn.p-n.io":4,"in.appcenter.ms":3,"b68f56edeceb6d2e33ce6c5eafcdd3d62fdb0e25.ipv4.cws.conviva.com":3,"id5-sync.com":3,"in-ftd-269.nl3.vip.prod.criteo.com":3,"clarity-ingest-eus-c-sc.eastus.cloudapp.azure.com":3,"btlr.sharethrough.com":3,"ib.anycast.adnxs.com":3,"in-ftd-170.nl3.vip.prod.criteo.com":3,"btlr-eu-central-1.sharethrough.com":3,"tag-euw.1rx.io":3,"pbserver.ezoic.com":3,"cell8011.fra.web.bid-eu.ads.aps.amazon-adsystem.com":3,"eur-bid-openpath.adsrvr.org":3,"prreqcroab.icu":3,"ogads-pa.clients6.google.com":3,"crashlyticsreports-pa.googleapis.com":3,"csp.withgoogle.com":3,"b68f56edeceb6d2e33ce6c5eafcdd3d62fdb0e25.ipv6.cws.conviva.com":2,"cws-usc1.conviva.com":2,"api.lab.eu.amplitude.com":2,"amplitude.map.fastly.net":2,"collect.tealiumiq.com":2,"pixel-config.reddit.com":2,"sb.scorecardresearch.com":2,"uk-script.dotmetrics.net":2,"a1.api.bbc.co.uk":2,"mybbc-analytics.files.bbci.co.uk":2,"securepubads.g.doubleclick.net":2,"gum.criteo.com":2,"web-banner.ads.aps.amazon-adsystem.com":2,"region1.analytics.google.com":2,"stats.g.doubleclick.net":2,"s.seedtag.com":2,"rtb.openx.net":2,"grid-bidder.criteo.com":2,"onetag-sys.com":2,"tagged-by.rubiconproject.net.akadns.net":2,"x15.adv.lijit.com":2,"prebid.trustedstack.com":2,"web.ads.aps.amazon-adsystem.com":2,"direct.adsrvr.org":2,"htlb.casalemedia.com":2,"hbopenbid.pubmatic.com":2,"eu-tlx.3lift.com":2,"hbopenbid-ams.pubmnet.com":2,"e62411ba26e55e979d33bc337c15a4a7.safeframe.googlesyndication.com":2,"pb-ing-02.ccgateway.net":2,"statics.smadex.com":2,"statics.prd.cdn.g.smadex.com":2,"cws-iad1.conviva.com":2,"cr-err.smadex.com":2,"tracker-batch.smadex.com":2,"ic3.events.data.microsoft.com":2,"teams.events.data.microsoft.com":2,"ipv6.cws.conviva.com":2,"cdn-settings.appsflyersdk.com":2,"combine.asnapieu.com":2,"region1.app-measurement.com":2,"c6thn4.cdn-settings.appsflyersdk.com":2,"collect-eu-central-1.tealiumiq.com":2,"visitor-service-eu-central-1.tealiumiq.com":2,"eu-aa.online-metrix.net":2,"log-beed83c9.eu.v2.we-stats.com":2,"cf.iadsdk.apple.com.akadns.net":2,"dit.whatsapp.net":2,"cws-euw1.conviva.com":2,"prod-event-relay-notes-api.v.aaplimg.com":2,"appsgrowthpromo-pa.googleapis.com":2,"mobile-collector.eu01.nr-data.net":1,"mobile-collector.eu01.nr-data.net.cdn.cloudflare.net":1,"a4621041136.cdn.optimizely.com":1,"cdn.cxense.com":1,"static.chartbeat.com":1,"cdn.gravitec.net":1,"analytics.ahrefs.com":1,"360playvid.info":1,"static.cloudflareinsights.com":1,"www.clarity.ms":1,"chimpstatic.com":1,"vmss-clarity-tag-sln.switzerlandnorth.cloudapp.azure.com":1,"cdn52184085.ahacdn.me":1,"mab.chartbeat.com":1,"serve.360playvid.info":1,"cdn0.360playvid.com":1,"cdn.id5-sync.com":1,"scripts.clarity.ms":1,"cdn.gravitec.media":1,"player-metrics.instaread.co":1,"cdn.adpushup.com":1,"go.ezodn.com":1,"aax.amazon-adsystem.com":1,"client.aps.amazon-adsystem.com":1,"config.aps.amazon-adsystem.com":1,"link.rubiconproject.com":1,"d1jvc9b8z3vcjs.cloudfront.net":1,"api.gravitec.media":1,"c.amazon-adsystem.com":1,"t.360playvid.info":1,"cdn.confiant-integrations.net":1,"e3.adpushup.com":1,"ocifeedbackorigin.apdc2n.adpushup.com":1,"secure.quantserve.com":1,"global.px.quantserve.com":1,"api.intentiq.com":1,"sync.intentiq.com":1,"id.crwdcntrl.net":1,"s0.2mdn.net":1,"pagead2.googlesyndication.com":1,"cdn.hadronid.net":1,"tags.crwdcntrl.net":1,"secure.cdn.fastclick.net":1,"s.clarity.ms":1,"carbon-cdn.ccgateway.net":1,"match.adsrvr.org":1,"id.a-mx.com":1,"ups.analytics.yahoo.com":1,"id.hadron.ad.gt":1,"image6.pubmatic.com":1,"at.teads.tv":1,"a.ad.gt":1,"lbs.eu-1-id5-sync.com":1,"lb.eu-1-id5-sync.com":1,"dcs-ups.g03.yahoodns.net":1,"id.hadron.ad.gt.cdn.cloudflare.net":1,"a.ad.gt.cdn.cloudflare.net":1,"pugm-amsfpairbc.pubmnet.com":1,"ads.servenobid.com":1,"ib.adnxs.com":1,"prebid-server.rubiconproject.com":1,"fastlane.rubiconproject.com":1,"prebid.smilewanted.com":1,"prebid.a-mo.net":1,"a.teads.tv":1,"ap.lijit.com":1,"exchange.kueezrtb.com":1,"targeting.unrulymedia.com":1,"ex.ingage.tech":1,"prebid-server-ips.rubiconproject.net.akadns.net":1,"nld-prebid.a-mx.net":1,"c3.a-mo.net":1,"istio-k8s-vidazoo-p-us-nyc1-c-external.vidazoo.services":1,"eventcollector.mcf-prod.a.intuit.com":1,"rules.quantcount.com":1,"pixel.quantserve.com":1,"ids.ad.gt":1,"ids4.ad.gt":1,"secure.adnxs.com":1,"u.openx.net":1,"image2.pubmatic.com":1,"token.rubiconproject.com":1,"cm.g.doubleclick.net":1,"sync.go.sonobi.com":1,"ad.360yield.com":1,"sync.smartadserver.com":1,"bh.contextweb.com":1,"p.ad.gt":1,"ids.ad.gt.cdn.cloudflare.net":1,"iad-2-sync.go.sonobi.com":1,"pixel.rubiconproject.net.akadns.net":1,"pug-ams-bc.pubmnet.com":1,"p.ad.gt.cdn.cloudflare.net":1,"am1-direct-bgp.contextweb.com":1,"euw-ice.360yield.com":1}}},{"date":"2026-06-23","total":518,"clients":{"10.10.10.10":{"http-intake.logs.us5.datadoghq.com":178,"www.pornhub.com":1,"www.bet365.com":1,"pornhub.com":1},"192.168.1.9":{"b3706b4d147b338e455c61c61223fa3f03dc73242e377721029d95badedd4bc.us-east-1.prod.service.minerva.devices.a2z.com":92,"unagi-eu.amazon.com":69,"api.mixpanel.com":20,"browser-intake-us5-datadoghq.com":17,"api.bitdrift.io":16,"app-analytics-services.com":10,"app-measurement.com":7,"cdn.p-n.io":5,"api3.branch.io":4,"securepubads.g.doubleclick.net":4,"o1158394.ingest.us.sentry.io":4,"in.appcenter.ms":4,"ad.doubleclick.net":3,"ogads-pa.clients6.google.com":2,"w3-reporting.reddit.com":2,"tpr0m7.launches.appsflyersdk.com":2,"pagead2.googlesyndication.com":2,"www.googletagservices.com":2,"d162h6x3rxav67.cloudfront.net":2,"region1.app-analytics-services.com":2,"metrics.icloud.com":2,"sentry.io":2,"googleads.g.doubleclick.net":2,"www.pornhub.com":1,"pornhub.com":1,"cdn.branch.io":1,"pixel-config.reddit.com":1,"olytics.omeda.com":1,"camp.fastcompany.com":1,"a.flower-byte.com":1,"d1mkq4fbm7j30i.cloudfront.net":1,"static.cloudflareinsights.com":1,"tpc.googlesyndication.com":1,"config.aps.amazon-adsystem.com":1,"ib.adnxs.com":1,"cdn.adsafeprotected.com":1,"segment-data-us-east.zqtk.net":1,"js-sec.indexww.com":1,"static.adsafeprotected.com":1,"lightning.cnn.com":1,"static.chartbeat.com":1,"z.cdp-dev.cnn.com":1,"linode-api.eu-west.proximic.com":1,"ib.anycast.adnxs.com":1,"cdn3.optimizely.com":1,"a125375509.cdn.optimizely.com":1,"live.rezync.com":1,"zion.api.cnn.io":1,"cdn.cxense.com":1,"ads.stickyadstv.com":1,"www.ugdturner.com":1,"8512b548-2306-4976-a576-a880f2c35e4e.edge.permutive.app":1,"btloader.com":1,"cadmus.script.ac":1,"id5-sync.com":1,"api.rlcdn.com":1,"ugdturner.com":1,"collector.cdp.cnn.com":1,"ad-delivery.net":1,"ab.dns-finder.com":1,"cdn.api.btloader.com":1,"cdn.btloader.com":1,"i.clean.gg":1,"api.btloader.com":1,"logx.optimizely.com":1,"buy.tinypass.com":1,"int.akisinn.info":1,"sdk.us-10.braze.com":1,"api-eu.mixpanel.com":1,"int.dewrain.site":1,"int.akisinn.site":1,"int.vaicore.xyz":1,"int.vaicore.store":1,"int.dewrain.world":1,"fbs.smoot.apple.com":1,"smoot-feedback.v.aaplimg.com":1,"ca.iadsdk.apple.com":1,"metrics-config.icloud.com":1,"kvinit-prod.api.kochava.com":1,"emrmrs.cdn-settings.appsflyersdk.com":1,"int.dewrain.life":1,"api.instabug.com":1,"api.permutive.app":1,"device-api.asnapieu.com":1,"combine.asnapieu.com":1}}}]}